bots/__init__.py
bots/tlg/__init__.py
bots/tlg/app/__init__.py
bots/tlg/app/utils.py
bots/tlg/bot/__init__.py
bots/tlg/bot/base.py
bots/tlg/bot/classes.py
bots/tlg/bot/example.py
bots/tlg/bot/util/__init__.py
bots/tlg/bot/util/enum.py
bots/tlg/bot/util/filteres.py
bots/tlg/bot/util/force_join.py
bots/tlg/bot/util/functions.py
bots/tlg/bot/util/packs.py
bots/tlg/bot/util/time_functions.py
starco_fastbot-1.2.0.dist-info/METADATA
starco_fastbot-1.2.0.dist-info/WHEEL
starco_fastbot-1.2.0.dist-info/top_level.txt
starco_fastbot-1.2.0.dist-info/RECORD
